f5xc_tops_py_client/__init__.py
f5xc_tops_py_client/cert.py
f5xc_tops_py_client/cred.py
f5xc_tops_py_client/group.py
f5xc_tops_py_client/helper.py
f5xc_tops_py_client/load_balancer.py
f5xc_tops_py_client/namespace_role.py
f5xc_tops_py_client/ns.py
f5xc_tops_py_client/origin_pool.py
f5xc_tops_py_client/registration.py
f5xc_tops_py_client/role.py
f5xc_tops_py_client/session.py
f5xc_tops_py_client/tenant.py
f5xc_tops_py_client/user.py
f5xc_tops_py_client/xcsite.py
f5xc_tops_py_client-0.3.3.dist-info/METADATA
f5xc_tops_py_client-0.3.3.dist-info/WHEEL
f5xc_tops_py_client-0.3.3.dist-info/RECORD
